delta/__init__.py
delta/delta.py
delta_ai-1.0.0.dist-info/licenses/LICENSE
img/delta-logo.png
img/file.png
img/file1.png
delta_ai-1.0.0.dist-info/METADATA
delta_ai-1.0.0.dist-info/WHEEL
delta_ai-1.0.0.dist-info/entry_points.txt
delta_ai-1.0.0.dist-info/top_level.txt
delta_ai-1.0.0.dist-info/RECORD
