Metadata-Version: 2.4
Name: delta-ai
Version: 1.0.0
Summary: Access open source LLMs in your local machine with CLI support
Home-page: https://github.com/oderoi/delta
Author: Nile AGI
Author-email: Nile AGI <support@nileagi.com>
Maintainer-email: Nile AGI <support@nileagi.com>
License-Expression: MIT
Project-URL: Homepage, https://github.com/oderoi/delta
Project-URL: Documentation, https://nileagi.com/products/delta
Project-URL: Repository, https://github.com/oderoi/delta
Project-URL: Bug Tracker, https://github.com/oderoi/delta/issues
Keywords: ai,llm,local,inference,ollama,cli,artificial intelligence,machine learning
Classifier: Development Status :: 4 - Beta
Classifier: Intended Audience :: Developers
Classifier: Intended Audience :: End Users/Desktop
Classifier: Operating System :: OS Independent
Classifier: Programming Language :: Python :: 3
Classifier: Programming Language :: Python :: 3.8
Classifier: Programming Language :: Python :: 3.9
Classifier: Programming Language :: Python :: 3.10
Classifier: Programming Language :: Python :: 3.11
Classifier: Programming Language :: Python :: 3.12
Classifier: Topic :: Scientific/Engineering :: Artificial Intelligence
Classifier: Topic :: Software Development :: Libraries :: Python Modules
Classifier: Topic :: System :: Systems Administration
Classifier: Topic :: Utilities
Requires-Python: >=3.8
License-File: LICENSE
Requires-Dist: rich
Requires-Dist: ollama
Requires-Dist: wikipedia
Requires-Dist: arxiv
Requires-Dist: Pillow
Requires-Dist: duckduckgo_search
Requires-Dist: PyPDF2
Requires-Dist: python-docx
Requires-Dist: prompt_toolkit
Requires-Dist: pyperclip
Requires-Dist: psutil
Requires-Dist: pynvml
Requires-Dist: py-cpuinfo
Provides-Extra: dev
Requires-Dist: pytest>=6.0; extra == "dev"
Requires-Dist: pytest-cov>=2.0; extra == "dev"
Requires-Dist: black>=21.0; extra == "dev"
Requires-Dist: flake8>=3.8; extra == "dev"
Requires-Dist: mypy>=0.800; extra == "dev"
Dynamic: author
Dynamic: home-page
Dynamic: license-file
Dynamic: requires-python
